pipeline_node_agents/__init__.py
pipeline_node_agents/adapters/__init__.py
pipeline_node_agents/adapters/base_adapter.py
pipeline_node_agents/adapters/crewai_adapter.py
pipeline_node_agents/adapters/python_fn_adapter.py
pipeline_node_agents/core/__init__.py
pipeline_node_agents/core/helpers/__init__.py
pipeline_node_agents/core/helpers/paths.py
pipeline_node_agents/core/helpers/pipeline_visualizer.py
pipeline_node_agents/core/logger_bootstrap.py
pipeline_node_agents/core/logging_config.py
pipeline_node_agents/core/node.py
pipeline_node_agents/core/pipeline.py
pipeline_node_agents/examples/__init__.py
pipeline_node_agents/examples/conditioning_pipeline.py
pipeline_node_agents/examples/input_checker_pipeline.py
pipeline_node_agents/examples/random_mean_pipeline.py
pipeline_node_agents/examples/random_mean_pipeline_crewai.py
pipeline_node_agents/examples/search_and_summarize.py
pipeline_node_agents/examples/trip_planner/__init__.py
pipeline_node_agents/examples/trip_planner/agents.py
pipeline_node_agents/examples/trip_planner/config.py
pipeline_node_agents/examples/trip_planner/functions.py
pipeline_node_agents/examples/trip_planner/nodes.py
pipeline_node_agents/examples/trip_planner/pipeline.py
pipeline_node_agents/tools/__init__.py
pipeline_node_agents/tools/scraper.py
pipeline_node_agents/tools/websearch.py
pipeline_node_agents-0.1.4.dist-info/METADATA
pipeline_node_agents-0.1.4.dist-info/WHEEL
pipeline_node_agents-0.1.4.dist-info/RECORD
