Metadata-Version: 2.4
Name: pipeline_node_agents
Version: 0.1.4
Summary: A lightweight Python framework for building modular AI pipelines with function nodes and agent nodes.
Author: Sergei Ovsiannikov
Author-email: a12230165@unet.univie.ac.at
Requires-Python: >=3.11,<3.14
Classifier: Programming Language :: Python :: 3
Classifier: Programming Language :: Python :: 3.11
Classifier: Programming Language :: Python :: 3.12
Classifier: Programming Language :: Python :: 3.13
Requires-Dist: beautifulsoup4 (>=4.14.3,<5.0.0)
Requires-Dist: crewai (>=1.6.1,<2.0.0) ; python_version >= "3.10" and python_version < "3.14"
Requires-Dist: ddgs (>=9.8.0,<10.0.0)
Requires-Dist: litellm (>=1.80.7,<2.0.0)
Requires-Dist: lxml (>=6.0.2,<7.0.0)
Requires-Dist: requests (>=2.32.0,<3.0.0)
Project-URL: Documentation, https://github.com/ser0vs/pipeline_node_agents/blob/master/docs/maintenance_guide.md
Project-URL: Homepage, https://github.com/ser0vs/pipeline_node_agents
Project-URL: Repository, https://github.com/ser0vs/pipeline_node_agents
